opal_fetcher_mysql/__init__.py
opal_fetcher_mysql/provider.py
opal_fetcher_mysql-1.0.3.dist-info/LICENSE
opal_fetcher_mysql-1.0.3.dist-info/METADATA
opal_fetcher_mysql-1.0.3.dist-info/WHEEL
opal_fetcher_mysql-1.0.3.dist-info/top_level.txt
opal_fetcher_mysql-1.0.3.dist-info/RECORD
