Metadata-Version: 2.1
Name: opal-fetcher-mysql
Version: 1.0.3
Summary: An OPAL fetch provider to bring authorization state from MySQL DB.
Author-email: Bhimesh Agrawal <bhimeshagrawalggc@gmail.com>
License: Apache-2.0
Project-URL: Source, https://github.com/bhimeshagrawal/opal-fetcher-mysql
Project-URL: Bug Tracker, https://github.com/bhimeshagrawal/opal-fetcher-mysql/issues
Keywords: Open Policy Agent,OPA,OPAL,Open Policy Administration Layer,MySQL,Permit.io
Classifier: Operating System :: OS Independent
Classifier: License :: OSI Approved :: Apache Software License
Classifier: Topic :: Software Development :: Libraries :: Python Modules
Classifier: Programming Language :: Python
Classifier: Programming Language :: Python :: 3
Classifier: Programming Language :: Python :: 3.7
Classifier: Programming Language :: Python :: 3.8
Classifier: Programming Language :: Python :: 3.9
Requires-Python: >=3.7
License-File: LICENSE
Requires-Dist: opal-common >=0.1.11
Requires-Dist: aiomysql
Requires-Dist: pydantic
Requires-Dist: tenacity
Requires-Dist: click
